COPYING
ChangeLog
INSTALL
INSTALL.cs
INSTALL.de
INSTALL.en_GB
INSTALL.es
INSTALL.et
INSTALL.fr
INSTALL.id
INSTALL.it
INSTALL.nl
INSTALL.pt_BR
INSTALL.ru
INSTALL.sk
INSTALL.sv
INSTALL.tr
INSTALL.uk
INSTALL.zh_CN
MANIFEST.in
README.cs
README.et
README.fr
README.rst
README.sv
README.tr
description-pak
setup.py
uninst.isl
wammu-configure.1
wammu-configure.py
wammu.1
wammu.appdata.xml.in
wammu.desktop.in
wammu.iss
wammu.py
wammu.spec
Wammu/About.py
Wammu/App.py
Wammu/BluezDiscovery.py
Wammu/Browser.py
Wammu/Calendar.py
Wammu/Composer.py
Wammu/ContactsXML.py
Wammu/Data.py
Wammu/Displayer.py
Wammu/EditContactList.py
Wammu/Editor.py
Wammu/Error.py
Wammu/ErrorLog.py
Wammu/ErrorMessage.py
Wammu/Events.py
Wammu/GammuSettings.py
Wammu/IMAP.py
Wammu/Image.py
Wammu/Info.py
Wammu/Locales.py
Wammu/Logger.py
Wammu/MailWriter.py
Wammu/Main.py
Wammu/Memory.py
Wammu/Message.py
Wammu/MessageDisplay.py
Wammu/OSUtils.py
Wammu/Paths.py
Wammu/PhoneSearch.py
Wammu/PhoneValidator.py
Wammu/PhoneWizard.py
Wammu/Reader.py
Wammu/Ringtone.py
Wammu/SMSExport.py
Wammu/SMSXML.py
Wammu/Select.py
Wammu/Settings.py
Wammu/SettingsStorage.py
Wammu/TalkbackDialog.py
Wammu/TalkbackFeaturesDialog.py
Wammu/Thread.py
Wammu/Todo.py
Wammu/Utils.py
Wammu/WammuSettings.py
Wammu/Webbrowser.py
Wammu/Wizard.py
Wammu/__init__.py
Wammu/test_imap.py
Wammu/test_paths.py
Wammu/test_utils.py
examples/sms.xsl
icon/wammu-14x14.png
icon/wammu-16x16.png
icon/wammu-192x192.png
icon/wammu-300x300.png
icon/wammu-32x32.png
icon/wammu-48x48.png
icon/wammu-64x64.png
icon/wammu-90x120.png
icon/wammu.ico
icon/wammu.png
icon/wammu.svg
icon/wammu.xpm
images/icons/calendar.png
images/icons/call-missed.png
images/icons/call-outgoing.png
images/icons/call-received.png
images/icons/call.png
images/icons/contact-phone.png
images/icons/contact-sim.png
images/icons/contact.png
images/icons/message-read.png
images/icons/message-sent.png
images/icons/message-unread.png
images/icons/message-unsent.png
images/icons/message.png
wammu.egg-info/PKG-INFO
wammu.egg-info/SOURCES.txt
wammu.egg-info/dependency_links.txt
wammu.egg-info/top_level.txt
