Metadata-Version: 1.1
Name: wammu
Version: 0.44
Summary: Wammu Mobile Phone Manager
Home-page: https://wammu.eu/wammu/
Author: Michal Cihar
Author-email: michal@cihar.com
License: GPLv3+
Download-URL: https://wammu.eu/download/wammu/
Keywords: mobile,phone,SMS,contact,gammu,calendar,todo
Platform: Linux
Platform: Mac OSX
Platform: Windows XP/2000/NT
Platform: Windows 95/98/ME
Classifier: Development Status :: 5 - Production/Stable
Classifier: Environment :: Win32 (MS Windows)
Classifier: Environment :: X11 Applications :: GTK
Classifier: Intended Audience :: End Users/Desktop
Classifier: License :: OSI Approved :: GNU General Public License v3 or later (GPLv3+)
Classifier: Operating System :: Microsoft :: Windows :: Windows 95/98/2000
Classifier: Operating System :: Microsoft :: Windows :: Windows NT/2000
Classifier: Operating System :: POSIX
Classifier: Operating System :: Unix
Classifier: Programming Language :: Python
Classifier: Topic :: Communications :: Telephony
Classifier: Topic :: Office/Business :: Scheduling
Classifier: Topic :: Utilities
Classifier: Natural Language :: English
Classifier: Natural Language :: Afrikaans
Classifier: Natural Language :: Catalan
Classifier: Natural Language :: Czech
Classifier: Natural Language :: German
Classifier: Natural Language :: Greek
Classifier: Natural Language :: Spanish
Classifier: Natural Language :: Finnish
Classifier: Natural Language :: French
Classifier: Natural Language :: Galician
Classifier: Natural Language :: Hebrew
Classifier: Natural Language :: Hungarian
Classifier: Natural Language :: Indonesian
Classifier: Natural Language :: Italian
Classifier: Natural Language :: Korean
Classifier: Natural Language :: Dutch
Classifier: Natural Language :: Polish
Classifier: Natural Language :: Portuguese (Brazilian)
Classifier: Natural Language :: Russian
Classifier: Natural Language :: Slovak
Classifier: Natural Language :: Swedish
Classifier: Natural Language :: Chinese (Simplified)
Classifier: Natural Language :: Chinese (Traditional)
